CLVP2/Feature_Engineering.py
CLVP2/TP.py
CLVP2/automated_model_performance.py
CLVP2/checks.py
CLVP2/model.py
CLVP2/modules.py
CLVP2/utils.py
CLVP2-0.7.dist-info/METADATA
CLVP2-0.7.dist-info/WHEEL
CLVP2-0.7.dist-info/top_level.txt
CLVP2-0.7.dist-info/RECORD
