Metadata-Version: 2.1
Name: CLVP2
Version: 0.7
Summary: customer lifetime value (clv) prediction
Home-page: UNKNOWN
Author: Omar Medhat
Author-email: omar.medhat965@gmail.com
License: UNKNOWN
Platform: UNKNOWN
